deepcv/__init__.py
deepcv/feature_column.py
deepcv/inputs.py
deepcv/utils.py
deepcv/contrib/__init__.py
deepcv/contrib/rnn.py
deepcv/contrib/rnn_v2.py
deepcv/contrib/utils.py
deepcv/estimator/__init__.py
deepcv/estimator/feature_column.py
deepcv/estimator/inputs.py
deepcv/estimator/utils.py
deepcv/estimator/models/__init__.py
deepcv/estimator/models/afm.py
deepcv/estimator/models/autoint.py
deepcv/estimator/models/ccpm.py
deepcv/estimator/models/dcn.py
deepcv/estimator/models/deepfefm.py
deepcv/estimator/models/deepfm.py
deepcv/estimator/models/fibinet.py
deepcv/estimator/models/fnn.py
deepcv/estimator/models/fwfm.py
deepcv/estimator/models/nfm.py
deepcv/estimator/models/pnn.py
deepcv/estimator/models/wdl.py
deepcv/estimator/models/xdeepfm.py
deepcv/layers/__init__.py
deepcv/layers/activation.py
deepcv/layers/core.py
deepcv/layers/interaction.py
deepcv/layers/normalization.py
deepcv/layers/sequence.py
deepcv/layers/utils.py
deepcv/models/__init__.py
deepcv/models/afm.py
deepcv/models/autoint.py
deepcv/models/ccpm.py
deepcv/models/dcn.py
deepcv/models/dcnmix.py
deepcv/models/deepfefm.py
deepcv/models/deepfm.py
deepcv/models/difm.py
deepcv/models/fgcnn.py
deepcv/models/fibinet.py
deepcv/models/flen.py
deepcv/models/fnn.py
deepcv/models/fwfm.py
deepcv/models/ifm.py
deepcv/models/mlr.py
deepcv/models/nfm.py
deepcv/models/onn.py
deepcv/models/pnn.py
deepcv/models/wdl.py
deepcv/models/xdeepfm.py
deepcv/models/multitask/__init__.py
deepcv/models/multitask/esmm.py
deepcv/models/multitask/mmoe.py
deepcv/models/multitask/ple.py
deepcv/models/multitask/sharedbottom.py
deepcv/models/sequence/__init__.py
deepcv/models/sequence/bst.py
deepcv/models/sequence/dien.py
deepcv/models/sequence/din.py
deepcv/models/sequence/dsin.py
src/__init__.py
src/example.py
deepcv-1.1.0.dist-info/METADATA
deepcv-1.1.0.dist-info/WHEEL
deepcv-1.1.0.dist-info/top_level.txt
deepcv-1.1.0.dist-info/RECORD
